[
    {
        "date": "2025-12-10",
        "gainers": [
            "PIPPIN",
            "SAD",
            "M",
            "STABLE",
            "FET"
        ]
    },
    {
        "date": "2025-12-11",
        "gainers": [
            "NIGHT",
            "PIPPIN",
            "ULTIMA",
            "M",
            "XDC"
        ]
    },
    {
        "date": "2025-12-12",
        "gainers": [
            "ZEC",
            "BAT",
            "MYX",
            "HASH",
            "M"
        ]
    },
    {
        "date": "2025-12-13",
        "gainers": [
            "BEAT",
            "STABLE",
            "AB",
            "MERL",
            "NIGHT"
        ]
    },
    {
        "date": "2025-12-14",
        "gainers": [
            "FOLKS",
            "M",
            "MERL",
            "MNT",
            "XPL"
        ]
    },
    {
        "date": "2025-12-15",
        "gainers": [
            "NIGHT",
            "BEAT",
            "RAIN",
            "MYX",
            "TRX"
        ]
    },
    {
        "date": "2025-12-15",
        "gainers": [
            "BEAT",
            "PIPPIN",
            "MYX",
            "XDC",
            "NFT"
        ]
    },
    {
        "date": "2025-12-16",
        "gainers": [
            "MON",
            "HASH",
            "XMR",
            "FARTCOIN",
            "APEPE"
        ]
    }
]